sjoa/__init__.py
sjoa/__main__.py
sjoa/decoder.py
sjoa/display.py
sjoa/parser.py
sjoa/utils.py
sjoa-1.3.1.dist-info/LICENSE
sjoa-1.3.1.dist-info/METADATA
sjoa-1.3.1.dist-info/WHEEL
sjoa-1.3.1.dist-info/entry_points.txt
sjoa-1.3.1.dist-info/top_level.txt
sjoa-1.3.1.dist-info/RECORD
