Metadata-Version: 2.1
Name: sjoa
Version: 1.3.1
Summary: Command-line tool to read metadata from torrent files or magnet URLs.
Home-page: https://github.com/barnumbirr/sjoa
Download-URL: https://github.com/barnumbirr/sjoa/archive/refs/heads/master.zip
Author: Martin Simon
Author-email: martin@simon.tf
Classifier: Development Status :: 5 - Production/Stable
Classifier: Intended Audience :: End Users/Desktop
Classifier: License :: OSI Approved :: Apache Software License
Classifier: Operating System :: OS Independent
Classifier: Programming Language :: Python :: 3
Classifier: Programming Language :: Python :: 3.8
Classifier: Programming Language :: Python :: 3.9
Classifier: Programming Language :: Python :: 3.10
Classifier: Programming Language :: Python :: 3.11
Classifier: Programming Language :: Python :: 3.12
License-File: LICENSE
Requires-Dist: bencodepy ==0.9.5
Requires-Dist: rich ==13.8.0
